advana/active.py
advana/activeDay.py
advana/activeImp.py
advana/activeUnit.py
advana/dashStatus.py
advana/daypartAnalysis.py
advana/locations.py
advana/rawDash.py
advana/rolling.py
advana/rollingLoc.py
advana/rollingSales.py
advana/__init__.py
advana/preprocess/active.py
advana/preprocess/__init__.py
advana/rolling/rolling.py
advana/rolling/__init__.py
advana-0.1.6.dist-info/DESCRIPTION.rst
advana-0.1.6.dist-info/METADATA
advana-0.1.6.dist-info/metadata.json
advana-0.1.6.dist-info/RECORD
advana-0.1.6.dist-info/top_level.txt
advana-0.1.6.dist-info/WHEEL
