Metadata-Version: 2.0
Name: advana
Version: 0.1.6
Summary: Advana Process Package
Home-page: UNKNOWN
Author: Ben DeVenezia
Author-email: <ben@advana.co>
License: UNKNOWN
Keywords: python,first package
Platform: UNKNOWN
Classifier: Development Status :: 3 - Alpha
Classifier: Intended Audience :: Education
Classifier: Programming Language :: Python :: 2
Classifier: Programming Language :: Python :: 3
Classifier: Operating System :: MacOS :: MacOS X
Classifier: Operating System :: Microsoft :: Windows
